Workbook

Sheet Start_Here
A1: EXCEL REAL-WORLD PROJECT: RETAIL SALES ANALYTICS
A3: Project objective | B3: Analyze retail sales, profit, monthly trends, regions, categories and channels.
A4: Dataset | B4: 500 synthetic sample order records for FY 2025. This is practice data, not real company data.
A5: Step 1 — Explore | B5: Open Sales_Data. Check columns, data types, dates, discounts, blanks and duplicates.
A6: Step 2 — Clean | B6: Practice Remove Duplicates, filters, date/number formatting and Excel Tables.
A7: Step 3 — Formulas | B7: Try SUMIFS, COUNTIFS, IF, IFERROR, XLOOKUP and calculate profit margin.
A8: Step 4 — PivotTables | B8: Create PivotTables for Sales by Month, Sales by Region, Profit by Category and Sales by Channel.
A9: Step 5 — Dashboard | B9: Review the starter Dashboard. Add slicers connected to your PivotTables for interactive filtering.
A10: Step 6 — Insights | B10: Write 3–5 findings: best month, top region, most profitable category, low-profit products and discount impact.
A11: Step 7 — Portfolio | B11: Save a final version, export the Dashboard as PDF, and describe the project on your resume.
A12: Interview practice | B12: Why can sales rise while profit falls? How do discounts affect profit? Which KPI would you show a manager?
A13: Important | B13: Dashboard uses formulas and charts as a starter. For a fully interactive dashboard, build PivotTables and slicers in desktop Excel.

Sheet Sales_Data
A1: Order ID | B1: Order Date | C1: Region | D1: Category | E1: Product | F1: Quantity | G1: Unit Price | H1: Discount | I1: Sales | J1: Cost | K1: Profit | L1: Channel | M1: Salesperson
A2: ORD-0001 | B2: 45760 | C2: East | D2: Electronics | E2: Wireless Mouse | F2: 4 | G2: 739.49 | H2: 0.1 | I2: 2662.16 | J2: 2105 | K2: 557.16 | L2: Online | M2: Meena
A3: ORD-0002 | B3: 45760 | C3: North | D3: Home & Kitchen | E3: Water Bottle | F3: 2 | G3: 422.55 | H3: 0 | I3: 845.1 | J3: 662.45 | K3: 182.65 | L3: Marketplace | M3: Vijay
A4: ORD-0003 | B4: 45757 | C4: North | D4: Electronics | E4: Wireless Mouse | F4: 3 | G4: 588.34 | H4: 0.2 | I4: 1412.02 | J4: 1367.47 | K4: 44.55 | L4: Online | M4: Meena
A5: ORD-0004 | B5: 45951 | C5: West | D5: Electronics | E5: Keyboard | F5: 2 | G5: 1134.55 | H5: 0 | I5: 2269.1 | J5: 1434.4 | K5: 834.7 | L5: Online | M5: Nisha
A6: ORD-0005 | B6: 45679 | C6: South | D6: Office Supplies | E6: Notebook Pack | F6: 5 | G6: 252 | H6: 0.02 | I6: 1234.8 | J6: 901.15 | K6: 333.65 | L6: Marketplace | M6: Vijay
A7: ORD-0006 | B7: 45827 | C7: South | D7: Office Supplies | E7: Printer Paper | F7: 4 | G7: 365.9 | H7: 0 | I7: 1463.6 | J7: 840.79 | K7: 622.81 | L7: Online | M7: Priya
A8: ORD-0007 | B8: 45708 | C8: West | D8: Electronics | E8: Wireless Mouse | F8: 4 | G8: 668.56 | H8: 0.05 | I8: 2540.53 | J8: 1504.37 | K8: 1036.16 | L8: Online | M8: Priya
A9: ORD-0008 | B9: 45964 | C9: North | D9: Office Supplies | E9: Printer Paper | F9: 7 | G9: 301.64 | H9: 0 | I9: 2111.48 | J9: 1702.27 | K9: 409.21 | L9: Marketplace | M9: Nisha
A10: ORD-0009 | B10: 45973 | C10: North | D10: Electronics | E10: USB Hub | F10: 6 | G10: 991.89 | H10: 0.02 | I10: 5832.31 | J10: 3430.18 | K10: 2402.13 | L10: Marketplace | M10: Rahul
A11: ORD-0010 | B11: 45997 | C11: North | D11: Office Supplies | E11: Pen Set | F11: 4 | G11: 181.81 | H11: 0 | I11: 727.24 | J11: 497.21 | K11: 230.03 | L11: Online | M11: Meena
A12: ORD-0011 | B12: 45692 | C12: South | D12: Office Supplies | E12: Notebook Pack | F12: 6 | G12: 249.44 | H12: 0 | I12: 1496.64 | J12: 1128.39 | K12: 368.25 | L12: Online | M12: Vijay
A13: ORD-0012 | B13: 45711 | C13: East | D13: Office Supplies | E13: File Folder | F13: 2 | G13: 145.87 | H13: 0 | I13: 291.74 | J13: 226.8 | K13: 64.94 | L13: Online | M13: Priya
... A501: ORD-0500 | B501: 46021 | C501: West | D501: Accessories | E501: Cable Organizer | F501: 4 | G501: 215.27 | H501: 0.02 | I501: 843.86 | J501: 664.06 | K501: 179.8 | L501: Online | M501: Nisha

Sheet Dashboard
A1: RETAIL SALES ANALYTICS DASHBOARD
A2: Sample business dataset | FY 2025 | Refresh formulas/charts after updating Sales_Data
A4: TOTAL SALES | B4: =SUM(Sales_Data!I2:I501) | C4: TOTAL PROFIT | D4: =SUM(Sales_Data!K2:K501) | E4: ORDERS | F4: =COUNTA(Sales_Data!A2:A501) | G4: PROFIT MARGIN | H4: =IFERROR(D4/B4,0)
A8: Month | B8: Sales | C8: Profit | E8: Region | F8: Sales
A9: 45658 | B9: =SUMIFS(Sales_Data!$I$2:$I$501,Sales_Data!$B$2:$B$501,">="&A9,Sales_Data!$B$2:$B$501,"<"&EDATE(A9,1)) | C9: =SUMIFS(Sales_Data!$K$2:$K$501,Sales_Data!$B$2:$B$501,">="&A9,Sales_Data!$B$2:$B$501,"<"&EDATE(A9,1)) | E9: North | F9: =SUMIF(Sales_Data!$C$2:$C$501,E9,Sales_Data!$I$2:$I$501)
A10: 45689 | B10: =SUMIFS(Sales_Data!$I$2:$I$501,Sales_Data!$B$2:$B$501,">="&A10,Sales_Data!$B$2:$B$501,"<"&EDATE(A10,1)) | C10: =SUMIFS(Sales_Data!$K$2:$K$501,Sales_Data!$B$2:$B$501,">="&A10,Sales_Data!$B$2:$B$501,"<"&EDATE(A10,1)) | E10: South | F10: =SUMIF(Sales_Data!$C$2:$C$501,E10,Sales_Data!$I$2:$I$501)
A11: 45717 | B11: =SUMIFS(Sales_Data!$I$2:$I$501,Sales_Data!$B$2:$B$501,">="&A11,Sales_Data!$B$2:$B$501,"<"&EDATE(A11,1)) | C11: =SUMIFS(Sales_Data!$K$2:$K$501,Sales_Data!$B$2:$B$501,">="&A11,Sales_Data!$B$2:$B$501,"<"&EDATE(A11,1)) | E11: East | F11: =SUMIF(Sales_Data!$C$2:$C$501,E11,Sales_Data!$I$2:$I$501)
A12: 45748 | B12: =SUMIFS(Sales_Data!$I$2:$I$501,Sales_Data!$B$2:$B$501,">="&A12,Sales_Data!$B$2:$B$501,"<"&EDATE(A12,1)) | C12: =SUMIFS(Sales_Data!$K$2:$K$501,Sales_Data!$B$2:$B$501,">="&A12,Sales_Data!$B$2:$B$501,"<"&EDATE(A12,1)) | E12: West | F12: =SUMIF(Sales_Data!$C$2:$C$501,E12,Sales_Data!$I$2:$I$501)
A13: 45778 | B13: =SUMIFS(Sales_Data!$I$2:$I$501,Sales_Data!$B$2:$B$501,">="&A13,Sales_Data!$B$2:$B$501,"<"&EDATE(A13,1)) | C13: =SUMIFS(Sales_Data!$K$2:$K$501,Sales_Data!$B$2:$B$501,">="&A13,Sales_Data!$B$2:$B$501,"<"&EDATE(A13,1))
A14: 45809 | B14: =SUMIFS(Sales_Data!$I$2:$I$501,Sales_Data!$B$2:$B$501,">="&A14,Sales_Data!$B$2:$B$501,"<"&EDATE(A14,1)) | C14: =SUMIFS(Sales_Data!$K$2:$K$501,Sales_Data!$B$2:$B$501,">="&A14,Sales_Data!$B$2:$B$501,"<"&EDATE(A14,1))
A15: 45839 | B15: =SUMIFS(Sales_Data!$I$2:$I$501,Sales_Data!$B$2:$B$501,">="&A15,Sales_Data!$B$2:$B$501,"<"&EDATE(A15,1)) | C15: =SUMIFS(Sales_Data!$K$2:$K$501,Sales_Data!$B$2:$B$501,">="&A15,Sales_Data!$B$2:$B$501,"<"&EDATE(A15,1)) | E15: Category | F15: Profit
A16: 45870 | B16: =SUMIFS(Sales_Data!$I$2:$I$501,Sales_Data!$B$2:$B$501,">="&A16,Sales_Data!$B$2:$B$501,"<"&EDATE(A16,1)) | C16: =SUMIFS(Sales_Data!$K$2:$K$501,Sales_Data!$B$2:$B$501,">="&A16,Sales_Data!$B$2:$B$501,"<"&EDATE(A16,1)) | E16: Electronics | F16: =SUMIF(Sales_Data!$D$2:$D$501,E16,Sales_Data!$K$2:$K$501)
A17: 45901 | B17: =SUMIFS(Sales_Data!$I$2:$I$501,Sales_Data!$B$2:$B$501,">="&A17,Sales_Data!$B$2:$B$501,"<"&EDATE(A17,1)) | C17: =SUMIFS(Sales_Data!$K$2:$K$501,Sales_Data!$B$2:$B$501,">="&A17,Sales_Data!$B$2:$B$501,"<"&EDATE(A17,1)) | E17: Home & Kitchen | F17: =SUMIF(Sales_Data!$D$2:$D$501,E17,Sales_Data!$K$2:$K$501)
A18: 45931 | B18: =SUMIFS(Sales_Data!$I$2:$I$501,Sales_Data!$B$2:$B$501,">="&A18,Sales_Data!$B$2:$B$501,"<"&EDATE(A18,1)) | C18: =SUMIFS(Sales_Data!$K$2:$K$501,Sales_Data!$B$2:$B$501,">="&A18,Sales_Data!$B$2:$B$501,"<"&EDATE(A18,1)) | E18: Office Supplies | F18: =SUMIF(Sales_Data!$D$2:$D$501,E18,Sales_Data!$K$2:$K$501)
A19: 45962 | B19: =SUMIFS(Sales_Data!$I$2:$I$501,Sales_Data!$B$2:$B$501,">="&A19,Sales_Data!$B$2:$B$501,"<"&EDATE(A19,1)) | C19: =SUMIFS(Sales_Data!$K$2:$K$501,Sales_Data!$B$2:$B$501,">="&A19,Sales_Data!$B$2:$B$501,"<"&EDATE(A19,1)) | E19: Accessories | F19: =SUMIF(Sales_Data!$D$2:$D$501,E19,Sales_Data!$K$2:$K$501)
A20: 45992 | B20: =SUMIFS(Sales_Data!$I$2:$I$501,Sales_Data!$B$2:$B$501,">="&A20,Sales_Data!$B$2:$B$501,"<"&EDATE(A20,1)) | C20: =SUMIFS(Sales_Data!$K$2:$K$501,Sales_Data!$B$2:$B$501,">="&A20,Sales_Data!$B$2:$B$501,"<"&EDATE(A20,1))
